CHANGELOG.md
LICENSE
README.rst
aftership/__init__.py
aftership/const.py
aftership/courier.py
aftership/estimated_delivery_date.py
aftership/exception.py
aftership/notification.py
aftership/request.py
aftership/response.py
aftership/tracking.py
aftership/util.py
aftership-1.4.1.dist-info/LICENSE
aftership-1.4.1.dist-info/WHEEL
aftership-1.4.1.dist-info/METADATA
aftership-1.4.1.dist-info/RECORD
