Metadata-Version: 2.1
Name: aftership
Version: 1.4.1
Summary: The python SDK of AfterShip API
Home-page: https://developers.aftership.com
License: MIT
Keywords: aftership,api,tracking,shipping,logistics
Author: AfterShip
Author-email: support@aftership.com
Requires-Python: >=3.6,<4.0
Classifier: Development Status :: 5 - Production/Stable
Classifier: Intended Audience :: Developers
Classifier: License :: OSI Approved :: MIT License
Classifier: Programming Language :: Python :: 3
Classifier: Programming Language :: Python :: 3.10
Classifier: Programming Language :: Python :: 3.6
Classifier: Programming Language :: Python :: 3.7
Classifier: Programming Language :: Python :: 3.8
Classifier: Programming Language :: Python :: 3.9
Classifier: Programming Language :: Python :: Implementation :: PyPy
Classifier: Topic :: Software Development
Requires-Dist: requests
Project-URL: Documentation, https://github.com/aftership/aftership-sdk-python
Project-URL: Repository, https://github.com/aftership/aftership-sdk-python
